molot/__init__.py
molot/_package.py
molot/_state.py
molot/_version.py
molot/core.py
molot/errors.py
molot/extras.py
molot-1.0.3.dist-info/LICENSE
molot-1.0.3.dist-info/METADATA
molot-1.0.3.dist-info/WHEEL
molot-1.0.3.dist-info/top_level.txt
molot-1.0.3.dist-info/RECORD
